BioVenn/BioVenn.py
BioVenn/__init__.py
BioVenn-1.1.3.dist-info/LICENSE
BioVenn-1.1.3.dist-info/METADATA
BioVenn-1.1.3.dist-info/WHEEL
BioVenn-1.1.3.dist-info/top_level.txt
BioVenn-1.1.3.dist-info/RECORD
