Metadata-Version: 2.1
Name: BioVenn
Version: 1.1.3
Summary: BioVenn: Create Area-Proportional Venn Diagrams from Biological Lists
Home-page: https://www.biovenn.nl
Author: Tim Hulsen
Author-email: thulsen@gmail.com
License: UNKNOWN
Platform: UNKNOWN
Classifier: Programming Language :: Python :: 3
Classifier: License :: OSI Approved :: GNU General Public License v3 (GPLv3)
Classifier: Operating System :: OS Independent
Requires-Dist: biomart (>=0.9.2)
Requires-Dist: matplotlib (>=3.3.3)
Requires-Dist: numpy (>=1.19.4)
